{"cameraMode":{"drawMode":0,"name":"Shaded","section":"Shading Mode"},"sceneLighting":true,"audioPlay":false,"sceneViewState":{"m_AlwaysRefresh":false,"showFog":true,"showSkybox":true,"showFlares":true,"showImageEffects":true,"showParticleSystems":true,"showVisualEffectGraphs":true,"m_FxEnabled":true},"in2DMode":false,"pivot":{"x":-4753.37060546875,"y":49.925872802734378,"z":288.9340515136719},"rotation":{"x":-0.2396129071712494,"y":0.41539961099624636,"z":-0.11466074734926224,"w":-0.8702130317687988},"size":22.721660614013673,"orthographic":false}